{
  "mockProducts": [
    {
      "id": "prod-1",
      "name": "Металлические конструкции",
      "description": "Производство и поставка металлических конструкций любой сложности для строительства",
      "category": "Строительные материалы",
      "type": "sell",
      "companyId": "company-4",
      "price": "от 50 000 руб/тонна",
      "createdAt": "{{date-10-days}}",
      "updatedAt": "{{date-2-days}}"
    },
    {
      "id": "prod-2",
      "name": "Стальные балки и профили",
      "description": "Высококачественные стальные балки и профили для промышленного строительства",
      "category": "Металлопрокат",
      "type": "sell",
      "companyId": "company-8",
      "price": "от 45 000 руб/тонна",
      "createdAt": "{{date-8-days}}",
      "updatedAt": "{{date-1-day}}"
    },
    {
      "id": "prod-3",
      "name": "Пластиковые изделия",
      "description": "Производство пластиковых изделий для различных отраслей промышленности",
      "category": "Пластик",
      "type": "sell",
      "companyId": "company-9",
      "price": "от 200 руб/кг",
      "createdAt": "{{date-15-days}}",
      "updatedAt": "{{date-3-days}}"
    },
    {
      "id": "prod-4",
      "name": "Строительные материалы",
      "description": "Полный спектр строительных материалов для жилого и коммерческого строительства",
      "category": "Строительные материалы",
      "type": "sell",
      "companyId": "company-1",
      "price": "по запросу",
      "createdAt": "{{date-20-days}}",
      "updatedAt": "{{date-5-days}}"
    },
    {
      "id": "prod-5",
      "name": "IT-решения для бизнеса",
      "description": "Разработка программного обеспечения и IT-консалтинг для предприятий",
      "category": "IT-услуги",
      "type": "sell",
      "companyId": "company-12",
      "price": "от 100 000 руб/проект",
      "createdAt": "{{date-12-days}}",
      "updatedAt": "{{date-2-days}}"
    },
    {
      "id": "prod-6",
      "name": "Логистические услуги",
      "description": "Комплексные логистические услуги по всей России и СНГ",
      "category": "Логистика",
      "type": "sell",
      "companyId": "company-5",
      "price": "от 15 руб/км",
      "createdAt": "{{date-18-days}}",
      "updatedAt": "{{date-4-days}}"
    },
    {
      "id": "prod-7",
      "name": "Пищевая продукция",
      "description": "Производство качественных продуктов питания для HoReCa и розничной торговли",
      "category": "Пищевая продукция",
      "type": "sell",
      "companyId": "company-15",
      "price": "по прайс-листу",
      "createdAt": "{{date-25-days}}",
      "updatedAt": "{{date-7-days}}"
    },
    {
      "id": "prod-8",
      "name": "Медицинское оборудование",
      "description": "Поставка современного медицинского оборудования и расходных материалов",
      "category": "Медицинское оборудование",
      "type": "sell",
      "companyId": "company-17",
      "price": "по запросу",
      "createdAt": "{{date-30-days}}",
      "updatedAt": "{{date-10-days}}"
    },
    {
      "id": "prod-9",
      "name": "Запчасти для спецтехники",
      "description": "Ищем надежного поставщика запчастей для строительной техники Caterpillar, Komatsu",
      "category": "Запчасти",
      "type": "buy",
      "companyId": "company-2",
      "budget": "до 500 000 руб",
      "createdAt": "{{date-5-days}}",
      "updatedAt": "{{date-1-day}}"
    },
    {
      "id": "prod-10",
      "name": "Сырье для производства",
      "description": "Требуется качественное сырье для производства пластиковых изделий",
      "category": "Сырье",
      "type": "buy",
      "companyId": "company-9",
      "budget": "до 1 000 000 руб",
      "createdAt": "{{date-7-days}}",
      "updatedAt": "{{date-2-days}}"
    },
    {
      "id": "prod-11",
      "name": "IT-оборудование",
      "description": "Закупка серверного оборудования и сетевого оборудования для офиса",
      "category": "IT-оборудование",
      "type": "buy",
      "companyId": "company-13",
      "budget": "до 2 000 000 руб",
      "createdAt": "{{date-3-days}}",
      "updatedAt": "{{date-1-day}}"
    },
    {
      "id": "prod-12",
      "name": "Консалтинговые услуги",
      "description": "Требуется консультация по оптимизации бизнес-процессов",
      "category": "Консалтинг",
      "type": "buy",
      "companyId": "company-14",
      "budget": "до 300 000 руб",
      "createdAt": "{{date-4-days}}",
      "updatedAt": "{{date-1-day}}"
    },
    {
      "id": "prod-13",
      "name": "Образовательные программы",
      "description": "Поиск поставщика корпоративного обучения для сотрудников",
      "category": "Образование",
      "type": "buy",
      "companyId": "company-18",
      "budget": "до 200 000 руб",
      "createdAt": "{{date-6-days}}",
      "updatedAt": "{{date-2-days}}"
    },
    {
      "id": "prod-14",
      "name": "Финансовые услуги",
      "description": "Требуется консультация по инвестиционному планированию",
      "category": "Финансовые услуги",
      "type": "buy",
      "companyId": "company-19",
      "budget": "до 150 000 руб",
      "createdAt": "{{date-2-days}}",
      "updatedAt": "{{date-1-day}}"
    }
  ]
}
